{
  "authorDailyContributionsMap": {
    "xCelestialPhoenix": [
      {
        "insertions": 130,
        "deletions": 21,
        "date": "2020-01-18",
        "commitResults": [
          {
            "hash": "d05f7e09f2b726355124d000d7badbf04f87043e",
            "messageTitle": "Added gradle support, plugins and dependencies",
            "messageBody": "",
            "insertions": 38,
            "deletions": 5
          },
          {
            "hash": "0e29bafa5d79850e5b9541f89d55c92e1eae177c",
            "messageTitle": "Added echo, and goodbye",
            "messageBody": "",
            "tags": [
              "Level-1"
            ],
            "insertions": 40,
            "deletions": 7
          },
          {
            "hash": "73cd03becc54e6112a188ba8578e0e8c6bf7e320",
            "messageTitle": "Added storing and listing functionalities",
            "messageBody": "",
            "tags": [
              "Level-2"
            ],
            "insertions": 9,
            "deletions": 1
          },
          {
            "hash": "d8f27b42b10a289148655c287d14c5ce7796796b",
            "messageTitle": "Added marking functionality",
            "messageBody": "",
            "tags": [
              "Level-3"
            ],
            "insertions": 43,
            "deletions": 8
          }
        ]
      },
      {
        "insertions": 438,
        "deletions": 88,
        "date": "2020-01-19",
        "commitResults": [
          {
            "hash": "8a0e071648a38242d7a146e290a0644d0db48224",
            "messageTitle": "Added different types of tasks",
            "messageBody": "",
            "tags": [
              "Level-4"
            ],
            "insertions": 115,
            "deletions": 16
          },
          {
            "hash": "ad6764030cd7ee563906ab792af130770141540e",
            "messageTitle": "Added batch testing",
            "messageBody": "",
            "tags": [
              "A-TextUiTesting"
            ],
            "insertions": 106,
            "deletions": 7
          },
          {
            "hash": "d3fdcbbee417b257d64c69c4b5bb7681a1cf1da7",
            "messageTitle": "Added exception handling",
            "messageBody": "",
            "tags": [
              "Level-5"
            ],
            "insertions": 186,
            "deletions": 61
          },
          {
            "hash": "afb7d10b9ccd1a1e7162052da4833ecc1bce7331",
            "messageTitle": "Added delete functionality",
            "messageBody": "",
            "tags": [
              "Level-6"
            ],
            "insertions": 31,
            "deletions": 4
          }
        ]
      },
      {
        "insertions": 170,
        "deletions": 62,
        "date": "2020-01-27",
        "commitResults": [
          {
            "hash": "946a437c33b06c74faabd6f9f8336c967adf0b71",
            "messageTitle": "Added loading and saving functionality",
            "messageBody": "",
            "tags": [
              "Level-7"
            ],
            "insertions": 85,
            "deletions": 8
          },
          {
            "hash": "e8c9ff832102075ecf4920808cdb7034d0b1b93b",
            "messageTitle": "Added date recognition",
            "messageBody": "",
            "insertions": 50,
            "deletions": 47
          },
          {
            "hash": "6d37f045b08d82a8178d6cde07e41f81099bb858",
            "messageTitle": "Added list task by date functionality",
            "messageBody": "",
            "tags": [
              "Level-8"
            ],
            "insertions": 35,
            "deletions": 7
          }
        ]
      },
      {
        "insertions": 616,
        "deletions": 236,
        "date": "2020-01-29",
        "commitResults": [
          {
            "hash": "3c23c5f4a0885159684fedcd2bcbe62f3b7060fe",
            "messageTitle": "Added testing",
            "messageBody": "",
            "insertions": 588,
            "deletions": 218
          },
          {
            "hash": "1006366989b2df51e2613cc88d78a6995af127e8",
            "messageTitle": "Updated testing",
            "messageBody": "",
            "tags": [
              "v0.1",
              "A-MoreOOP",
              "A-JUnit"
            ],
            "insertions": 28,
            "deletions": 18
          }
        ]
      },
      {
        "insertions": 710,
        "deletions": 297,
        "date": "2020-01-30",
        "commitResults": [
          {
            "hash": "74f4577dc25554eeb02b35fcbea35881e4ef300a",
            "messageTitle": "Updated coding standard",
            "messageBody": "",
            "insertions": 100,
            "deletions": 100
          },
          {
            "hash": "e73b04e4fc4229ffedd30f30c7041b7bdbeea05b",
            "messageTitle": "Updated JavaDoc",
            "messageBody": "",
            "insertions": 493,
            "deletions": 105
          },
          {
            "hash": "ee1123eade55cdc2d48d61a325e8de2eab22d2cf",
            "messageTitle": "Added find functionality",
            "messageBody": "",
            "tags": [
              "Level-9"
            ],
            "insertions": 117,
            "deletions": 92
          }
        ]
      },
      {
        "insertions": 46,
        "deletions": 33,
        "date": "2020-02-02",
        "commitResults": [
          {
            "hash": "b643d792584d955de080e2dd2703bb1485b31b25",
            "messageTitle": "Added checkstyle",
            "messageBody": "",
            "tags": [
              "A-CheckStyle"
            ],
            "insertions": 46,
            "deletions": 33
          }
        ]
      },
      {
        "insertions": 720,
        "deletions": 362,
        "date": "2020-02-05",
        "commitResults": [
          {
            "hash": "829ddfc0491e8e0f9a49dfe2c79a99ce4eb9faf1",
            "messageTitle": "Added GUI",
            "messageBody": "",
            "tags": [
              "Level-10"
            ],
            "insertions": 720,
            "deletions": 362
          }
        ]
      },
      {
        "insertions": 34,
        "deletions": 2,
        "date": "2020-02-09",
        "commitResults": [
          {
            "hash": "332a6fe23ec607647e34cfef9cbaa74b86093ca0",
            "messageTitle": "Resolved dialog box truncating",
            "messageBody": "",
            "insertions": 1,
            "deletions": 1
          },
          {
            "hash": "bbbbb42abfa82d7267830d30c712eec04d0c9880",
            "messageTitle": "Resolved JavaFx runtime components missing for jar",
            "messageBody": "",
            "insertions": 33,
            "deletions": 1
          }
        ]
      },
      {
        "insertions": 878,
        "deletions": 372,
        "date": "2020-02-10",
        "commitResults": [
          {
            "hash": "b23f980e3877c91610ea72ba5bc8f6db37dc6d05",
            "messageTitle": "Improved code quality",
            "messageBody": "",
            "tags": [
              "A-CodeQuality"
            ],
            "insertions": 878,
            "deletions": 372
          }
        ]
      },
      {
        "insertions": 72,
        "deletions": 50,
        "date": "2020-02-12",
        "commitResults": [
          {
            "hash": "ce87afd91b14ef03bab4066983c8a08f862e934b",
            "messageTitle": "Added assertions",
            "messageBody": "",
            "tags": [
              "A-Assertions"
            ],
            "insertions": 72,
            "deletions": 50
          }
        ]
      }
    ]
  },
  "authorFinalContributionMap": {
    "xCelestialPhoenix": 2229
  },
  "authorFileTypeContributionMap": {
    "xCelestialPhoenix": {
      "java": 2032,
      "md": 2,
      "fxml": 54,
      "sh": 0,
      "bat": 21,
      "gradle": 45,
      "txt": 75
    }
  },
  "authorContributionVariance": {
    "xCelestialPhoenix": 126776.586
  },
  "authorDisplayNameMap": {
    "xCelestialPhoenix": "CS2103T-F10- 3 NG J..ENCE"
  }
}
