{
  "authorDailyContributionsMap": {
    "raivatshah": [
      {
        "insertions": 284,
        "deletions": 30,
        "date": "2020-01-26",
        "commitResults": [
          {
            "hash": "8b0c4055ee76604f259ca175e57b4b42d198e4aa",
            "messageTitle": "Level-1",
            "messageBody": "",
            "tags": [
              "Level-1"
            ],
            "insertions": 14,
            "deletions": 6
          },
          {
            "hash": "d9697d9f5afe0a4cb79b062d1e6730b2d2b7a422",
            "messageTitle": "Level-2",
            "messageBody": "",
            "tags": [
              "Level-2"
            ],
            "insertions": 12,
            "deletions": 1
          },
          {
            "hash": "c63f269afaebbf2abee19de0bb4ef99b841f6b48",
            "messageTitle": "Level-3",
            "messageBody": "",
            "tags": [
              "Level-3"
            ],
            "insertions": 45,
            "deletions": 2
          },
          {
            "hash": "f74bc922c1ca82186174f324dac219fc2d61e985",
            "messageTitle": "Add subclasses",
            "messageBody": "",
            "insertions": 81,
            "deletions": 0
          },
          {
            "hash": "010ff62ffc2e3bf328e5883785d5ad923eee4bd1",
            "messageTitle": "Level-4",
            "messageBody": "",
            "tags": [
              "Level-4"
            ],
            "insertions": 22,
            "deletions": 2
          },
          {
            "hash": "dbb00ece3bc1f71dd57caf766f4ab127e0abbb72",
            "messageTitle": "A-TextUiTesting",
            "messageBody": "",
            "tags": [
              "A-TextUiTesting"
            ],
            "insertions": 59,
            "deletions": 0
          },
          {
            "hash": "a2454dfc7ec8b7e4342bae75d9ab6bad81546add",
            "messageTitle": "Level-5",
            "messageBody": "",
            "tags": [
              "Level-5"
            ],
            "insertions": 43,
            "deletions": 18
          },
          {
            "hash": "3ed51583723cebccf179339f88515d79781a5a9a",
            "messageTitle": "Level-6",
            "messageBody": "",
            "tags": [
              "Level-6"
            ],
            "insertions": 8,
            "deletions": 1
          }
        ]
      },
      {
        "insertions": 1,
        "deletions": 1,
        "date": "2020-02-01",
        "commitResults": [
          {
            "hash": "60f8bbdd5c6a9e9dd3110a723a029cdd8136fa86",
            "messageTitle": "fix error with firstWord",
            "messageBody": "",
            "insertions": 1,
            "deletions": 1
          }
        ]
      },
      {
        "insertions": 96,
        "deletions": 49,
        "date": "2020-02-03",
        "commitResults": [
          {
            "hash": "234dc1d12f54cdce74338fa9d83d94632162aac2",
            "messageTitle": "make Duke class more OOP style",
            "messageBody": "",
            "insertions": 96,
            "deletions": 49
          }
        ]
      },
      {
        "insertions": 130,
        "deletions": 17,
        "date": "2020-02-04",
        "commitResults": [
          {
            "hash": "d3fa6618c48cfb5531aeea92010937ec7f51f604",
            "messageTitle": "Level-7",
            "messageBody": "",
            "insertions": 92,
            "deletions": 13
          },
          {
            "hash": "95c0efb3c932f6a2200448f20f54d02739732e9f",
            "messageTitle": "add code for Level-8",
            "messageBody": "",
            "insertions": 31,
            "deletions": 3
          },
          {
            "hash": "274fa826f503deb4e145cdc5351243a74f26531f",
            "messageTitle": "setup gradle",
            "messageBody": "",
            "tags": [
              "A-Gradle"
            ],
            "insertions": 2,
            "deletions": 1
          },
          {
            "hash": "1b1fbc2333f6af0ed9ed3fe88bd4e8d601ba7231",
            "messageTitle": "Add checkstyle in Graddle",
            "messageBody": "",
            "tags": [
              "A-CheckStyle"
            ],
            "insertions": 5,
            "deletions": 0
          }
        ]
      },
      {
        "insertions": 421,
        "deletions": 191,
        "date": "2020-02-11",
        "commitResults": [
          {
            "hash": "035daeae2699b6a5eb650f2527ada9ab5194afc8",
            "messageTitle": "Make code more OOP",
            "messageBody": "",
            "tags": [
              "v1.2",
              "A-MoreOOP"
            ],
            "insertions": 296,
            "deletions": 170
          },
          {
            "hash": "44fdd79f7bf805609e03496b69acfe4342ec315c",
            "messageTitle": "A-Packages",
            "messageBody": "",
            "tags": [
              "A-Packages"
            ],
            "insertions": 13,
            "deletions": 2
          },
          {
            "hash": "43b110a91b522cce2f2a1352b6e1fff48934722b",
            "messageTitle": "A-JUnit",
            "messageBody": "",
            "tags": [
              "A-JUnit",
              "0.1.3"
            ],
            "insertions": 38,
            "deletions": 1
          },
          {
            "hash": "5efd9144c88b0980f86cb45a4f0dc9c719f83462",
            "messageTitle": "Add JavaDoc comments",
            "messageBody": "",
            "tags": [
              "A-JavaDoc"
            ],
            "insertions": 47,
            "deletions": 18
          },
          {
            "hash": "5b29a37b735ea98cd779c7c06feb48ee930cc7b8",
            "messageTitle": "Add find functionality",
            "messageBody": "",
            "insertions": 27,
            "deletions": 0
          }
        ]
      },
      {
        "insertions": 95,
        "deletions": 7,
        "date": "2020-02-15",
        "commitResults": [
          {
            "hash": "221e0f42d4f5ddf72821d96d553afa4ae1e811c1",
            "messageTitle": "add JavaFX to build.gradle",
            "messageBody": "",
            "insertions": 14,
            "deletions": 0
          },
          {
            "hash": "fc4053e62cd42b9c8be8c473a3ae469e863cf9e6",
            "messageTitle": "JavaFX Tutorial Part 1",
            "messageBody": "",
            "insertions": 29,
            "deletions": 1
          },
          {
            "hash": "7614f09eaad4ecd6bf99df3efd2c18b3d1458422",
            "messageTitle": "JavaFX Tutorial Part 2",
            "messageBody": "",
            "insertions": 52,
            "deletions": 6
          }
        ]
      },
      {
        "insertions": 324,
        "deletions": 171,
        "date": "2020-02-16",
        "commitResults": [
          {
            "hash": "d81cae41dd14eeab0fee726a2351039104a1af7e",
            "messageTitle": "JavaFX Level-3",
            "messageBody": "",
            "insertions": 106,
            "deletions": 0
          },
          {
            "hash": "e7e20c2270c4f09efaa7dc5b95ab10ac391aee41",
            "messageTitle": "Level-10",
            "messageBody": "",
            "tags": [
              "Level-10"
            ],
            "insertions": 217,
            "deletions": 171
          },
          {
            "hash": "742ff9cf16729734ec675f53fa14c04f3bcc2a39",
            "messageTitle": "Code for Level 10 GUI",
            "messageBody": "",
            "insertions": 1,
            "deletions": 0
          }
        ]
      },
      {
        "insertions": 101,
        "deletions": 82,
        "date": "2020-02-18",
        "commitResults": [
          {
            "hash": "7ecfa537e167947acbd7db57f903def9f28f7147",
            "messageTitle": "A-Assertions",
            "messageBody": "",
            "tags": [
              "A-Assertions"
            ],
            "insertions": 10,
            "deletions": 43
          },
          {
            "hash": "d9ba202e06043a93c528d08741e9728c9472b0ee",
            "messageTitle": "Refactoring Code Part 1",
            "messageBody": "",
            "insertions": 60,
            "deletions": 24
          },
          {
            "hash": "68d0d4f944922efcfa47380cf943e0700cc40a92",
            "messageTitle": "A-CodeQuality Part 2",
            "messageBody": "",
            "tags": [
              "A-CodeQuality"
            ],
            "insertions": 8,
            "deletions": 4
          },
          {
            "hash": "a81a527fd7ec0af4952db542190bbe812b4ab1aa",
            "messageTitle": "fix minor bugs",
            "messageBody": "",
            "insertions": 7,
            "deletions": 6
          },
          {
            "hash": "e0a93711ba1a163272e10912ebb36c4e2a5a8e7e",
            "messageTitle": "Set up Travis CI",
            "messageBody": "",
            "insertions": 8,
            "deletions": 5
          },
          {
            "hash": "c7aae11f160ed6f047491a08645bbca755f91a87",
            "messageTitle": "A-UserGuide",
            "messageBody": "",
            "tags": [
              "A-UserGuide"
            ],
            "insertions": 8,
            "deletions": 0
          }
        ]
      },
      {
        "insertions": 604,
        "deletions": 610,
        "date": "2020-02-20",
        "commitResults": [
          {
            "hash": "8f09835dbb62de7e80b601b631ee42daeb537f54",
            "messageTitle": "fix checkstyle issues",
            "messageBody": "",
            "insertions": 604,
            "deletions": 610
          }
        ]
      },
      {
        "insertions": 631,
        "deletions": 566,
        "date": "2020-02-22",
        "commitResults": [
          {
            "hash": "7ebd83db8a63dadc37ca280fe31cb8c4004de77a",
            "messageTitle": "fix checkstyle issues",
            "messageBody": "",
            "insertions": 631,
            "deletions": 566
          }
        ]
      },
      {
        "insertions": 215,
        "deletions": 101,
        "date": "2020-02-23",
        "commitResults": [
          {
            "hash": "3f29a633195ca290a0635c8905cf844c64266e9e",
            "messageTitle": "fix all checkstyle issues",
            "messageBody": "",
            "insertions": 121,
            "deletions": 72
          },
          {
            "hash": "6d21332497593679db258766d4ab517d50b58394",
            "messageTitle": "Update User guide part 1",
            "messageBody": "",
            "insertions": 49,
            "deletions": 12
          },
          {
            "hash": "887f03ded43192b3176c0dd8b5c703397b7858bc",
            "messageTitle": "add C-FriendlierSyntax",
            "messageBody": "",
            "tags": [
              "C-FriendlierSyntax"
            ],
            "insertions": 38,
            "deletions": 16
          },
          {
            "hash": "481111cf19a60621529fe8aea4759ac2266cf410",
            "messageTitle": "finish UserGuide",
            "messageBody": "",
            "insertions": 7,
            "deletions": 1
          }
        ]
      },
      {
        "insertions": 33,
        "deletions": 28,
        "date": "2020-02-24",
        "commitResults": [
          {
            "hash": "ced162a111aad7ab1011c359185a6d360b0f96e2",
            "messageTitle": "fix UI and filestorage",
            "messageBody": "",
            "tags": [
              "v0.2",
              "v0.1"
            ],
            "insertions": 33,
            "deletions": 28
          }
        ]
      }
    ]
  },
  "authorFinalContributionMap": {
    "raivatshah": 1085
  },
  "authorFileTypeContributionMap": {
    "raivatshah": {
      "java": 887,
      "md": 65,
      "fxml": 36,
      "sh": 34,
      "bat": 0,
      "gradle": 34,
      "txt": 29
    }
  },
  "authorContributionVariance": {
    "raivatshah": 76319.516
  },
  "authorDisplayNameMap": {
    "raivatshah": "CS2103-W14- 4 RAIV..SHAH"
  }
}
