{
  "authorDailyContributionsMap": {
    "IYVVVVV": [
      {
        "insertions": 64,
        "deletions": 0,
        "date": "2020-01-22",
        "commitResults": [
          {
            "hash": "cbd24a6b7a4010e68136daba22b89486c50b5608",
            "messageTitle": "Add text-ui-test",
            "messageBody": "",
            "insertions": 21,
            "deletions": 0
          },
          {
            "hash": "247d1f3298df86ca25b4484597c373f931838b68",
            "messageTitle": "Create Ignore-file-list. Add input.txt and EXPECTED.txt into the ingored list.",
            "messageBody": "",
            "insertions": 2,
            "deletions": 0
          },
          {
            "hash": "80689f0441f59afaa5b7348f4d46ee586ee0f7f6",
            "messageTitle": "Add Greet, Echo and Exit",
            "messageBody": "",
            "insertions": 41,
            "deletions": 0
          }
        ]
      },
      {
        "insertions": 336,
        "deletions": 45,
        "date": "2020-01-23",
        "commitResults": [
          {
            "hash": "52f38b1771d13a75aaf9d54e56edb79d25b11505",
            "messageTitle": "update Add and List function.",
            "messageBody": "",
            "insertions": 24,
            "deletions": 2
          },
          {
            "hash": "64cd694956ef757e5f94496726347f1ba6dc55d8",
            "messageTitle": "Add Task class.",
            "messageBody": "",
            "insertions": 13,
            "deletions": 0
          },
          {
            "hash": "f97f278dbe01eb6c21a9b4850421ce6376f925f7",
            "messageTitle": "Add getDescription.",
            "messageBody": "",
            "insertions": 4,
            "deletions": 0
          },
          {
            "hash": "cf444ad31df4e4db32ee90b85a970e86ab2f9e63",
            "messageTitle": "Store tasks in Arraylist. Change list display.",
            "messageBody": "",
            "insertions": 15,
            "deletions": 10
          },
          {
            "hash": "d7767c5450687b965035cb9ae500cd4a8d9fc794",
            "messageTitle": "Add MarkAsDone function to tasks.",
            "messageBody": "",
            "insertions": 25,
            "deletions": 5
          },
          {
            "hash": "850f5fbeea082b4e019dbcb05b5a2ee36e0c877f",
            "messageTitle": "Add Todo, Deadline and Event as sub-class of Task.",
            "messageBody": "",
            "insertions": 75,
            "deletions": 9
          },
          {
            "hash": "1f9f4162e2e07e4aa0965b86a64ff991af6969f1",
            "messageTitle": "Handle errors for empty todo task name and wrong task input format.",
            "messageBody": "",
            "insertions": 11,
            "deletions": 10
          },
          {
            "hash": "ca70ddf99b04c5b00c724706f34caeddbf7f4b28",
            "messageTitle": "Add delete function.",
            "messageBody": "",
            "insertions": 12,
            "deletions": 0
          },
          {
            "hash": "ff107e0c84f86a5a19849bfd0216173561a358c5",
            "messageTitle": "Add comments to each method. Handle error of delete/done nonexistent tasks and incorrect input for Deadline and Event.",
            "messageBody": "",
            "insertions": 157,
            "deletions": 9
          }
        ]
      },
      {
        "insertions": 86,
        "deletions": 18,
        "date": "2020-01-29",
        "commitResults": [
          {
            "hash": "c46b387e869716735b7b01f10dd98051eefdfaa6",
            "messageTitle": "Save user task list into a txt file under \u0027data\u0027 directory.",
            "messageBody": "",
            "insertions": 32,
            "deletions": 0
          },
          {
            "hash": "261c0eb0931b2316a68330cf92ac1de27f3b1260",
            "messageTitle": "Add data file.",
            "messageBody": "",
            "insertions": 1,
            "deletions": 0
          },
          {
            "hash": "605a149a3fc56912239111ebf35372ea20a917f6",
            "messageTitle": "Define task format when store in txt file.",
            "messageBody": "",
            "insertions": 19,
            "deletions": 0
          },
          {
            "hash": "a6fb7533ec6769954c8b41eb580c27597c5e1e99",
            "messageTitle": "no message",
            "messageBody": "",
            "insertions": 1,
            "deletions": 0
          },
          {
            "hash": "edc525e9d1d80d67bc5a3fcbaad05b4871b48450",
            "messageTitle": "Change date format.",
            "messageBody": "",
            "insertions": 21,
            "deletions": 10
          },
          {
            "hash": "c89a3be28d89f985015dfc4716a8cbc4b39bb33b",
            "messageTitle": "Change import order to avoid merge conflicts.",
            "messageBody": "",
            "insertions": 1,
            "deletions": 1
          },
          {
            "hash": "0f23e439ca3f629e47b8c7dca4121a16faf67ba0",
            "messageTitle": "Specify exceptions to avoid merge conflicts.",
            "messageBody": "",
            "insertions": 10,
            "deletions": 2
          },
          {
            "hash": "a31b1c9732fd6a3973f0c57ec6bace99e12e67cb",
            "messageTitle": "Change to update data file after user\u0027s every input.",
            "messageBody": "",
            "insertions": 1,
            "deletions": 5
          }
        ]
      },
      {
        "insertions": 436,
        "deletions": 219,
        "date": "2020-01-30",
        "commitResults": [
          {
            "hash": "a1016ec796837de0aac95d7c06e00806fd32664c",
            "messageTitle": "Add data file.",
            "messageBody": "",
            "insertions": 1,
            "deletions": 0
          },
          {
            "hash": "837bff322475c8e53d43ff6948ef171c5c124ee4",
            "messageTitle": "Add Ui class to read user input and give output.",
            "messageBody": "",
            "insertions": 82,
            "deletions": 0
          },
          {
            "hash": "27782c5e0f8b6e303e0814a820649195a99e0a10",
            "messageTitle": "Add Storage class to load and save tasks data file.",
            "messageBody": "",
            "insertions": 79,
            "deletions": 0
          },
          {
            "hash": "2af31bf8c382f89a9eacf485cf399e3d56081d3a",
            "messageTitle": "Add TaskList class to handle tasks.",
            "messageBody": "",
            "insertions": 29,
            "deletions": 0
          },
          {
            "hash": "bb9ec6174bc28df675d178380e4e27dda629c5b8",
            "messageTitle": "Make Duke more OOP.",
            "messageBody": "",
            "insertions": 41,
            "deletions": 195
          },
          {
            "hash": "efec51a7093fe89c953bec8e363848c14cc114bf",
            "messageTitle": "Use Gradle to test Todo class.",
            "messageBody": "",
            "insertions": 28,
            "deletions": 3
          },
          {
            "hash": "9bd88dfeb838b277eafb871416a32c12d6c66751",
            "messageTitle": "Use Gradle to create Jar file.",
            "messageBody": "",
            "insertions": 9,
            "deletions": 0
          },
          {
            "hash": "95896c95389f3a131f4d6387f44fd9e47d336537",
            "messageTitle": "Update messages when File Error happens.",
            "messageBody": "",
            "insertions": 1,
            "deletions": 1
          },
          {
            "hash": "d5d8809535a2d0d4280f95005f54a269aead947d",
            "messageTitle": "Add JavaDoc comments to the code.",
            "messageBody": "",
            "insertions": 112,
            "deletions": 1
          },
          {
            "hash": "2c289c35937c711e30389ab9c75fa51078110079",
            "messageTitle": "Use Gradle-checkstyle to correct code to stantard.",
            "messageBody": "",
            "insertions": 28,
            "deletions": 19
          },
          {
            "hash": "a8d7edcd96bc546c1509a661a5edaa524b0e2a99",
            "messageTitle": "Add find to find tasks by given key words.",
            "messageBody": "",
            "insertions": 26,
            "deletions": 0
          }
        ]
      },
      {
        "insertions": 66,
        "deletions": 63,
        "date": "2020-02-03",
        "commitResults": [
          {
            "hash": "0c03674608325c92c2cabcb931db39b13573ad18",
            "messageTitle": "Uses Gradle Checkstyle to correct style error.",
            "messageBody": "",
            "insertions": 66,
            "deletions": 63
          }
        ]
      },
      {
        "insertions": 430,
        "deletions": 151,
        "date": "2020-02-04",
        "commitResults": [
          {
            "hash": "1ad436768c915921defda120bd6ffe3636e23571",
            "messageTitle": "Add a GUI to Duke.",
            "messageBody": "",
            "insertions": 430,
            "deletions": 151
          }
        ]
      }
    ]
  },
  "authorFinalContributionMap": {
    "IYVVVVV": 930
  },
  "authorFileTypeContributionMap": {
    "IYVVVVV": {
      "gitignore": 5,
      "gradle": 36,
      "properties": 3,
      "java": 38,
      "java": 38,
      "java": 19,
      "java": 78,
      "java": 29,
      "java": 40,
      "java": 6,
      "java": 10,
      "java": 6,
      "java": 6,
      "java": 10,
      "java": 6,
      "java": 33,
      "java": 56,
      "java": 19,
      "java": 11,
      "java": 32,
      "java": 99,
      "java": 63,
      "java": 61,
      "java": 29,
      "java": 125,
      "fxml": 16,
      "fxml": 19,
      "java": 16,
      "bat": 21
    }
  },
  "authorContributionVariance": {
    "IYVVVVV": 25900.594
  },
  "authorDisplayNameMap": {
    "IYVVVVV": "CS2103-T09- 4 YE C..CHEN"
  }
}
