{
  "authorDailyContributionsMap": {
    "nhamhung": [
      {
        "insertions": 299,
        "deletions": 67,
        "date": "2020-01-23",
        "commitResults": [
          {
            "hash": "0c8d8ac6f4893bb974a05f168495f5327312dc80",
            "messageTitle": "add Level-1",
            "messageBody": "",
            "tags": [
              "Level-1"
            ],
            "insertions": 13,
            "deletions": 0
          },
          {
            "hash": "61e0c5012826a16cf7685482d2858a27a2ee8e7b",
            "messageTitle": "Level 2. Add, List",
            "messageBody": "",
            "insertions": 14,
            "deletions": 4
          },
          {
            "hash": "ff12e4f344231cc424a8ce80088ae4778e0c1f4b",
            "messageTitle": "Level 2. Add, List",
            "messageBody": "",
            "tags": [
              "Level-2"
            ],
            "insertions": 1,
            "deletions": 0
          },
          {
            "hash": "7f6585ba5a85a7652703229010f2ece9cf9aff3a",
            "messageTitle": "Level 3. Mark as Done",
            "messageBody": "",
            "tags": [
              "Level-3"
            ],
            "insertions": 48,
            "deletions": 10
          },
          {
            "hash": "c2036473e0500f2f85d04490177fb7363cb14f37",
            "messageTitle": "Level 4. ToDos, Events, Deadlines",
            "messageBody": "",
            "tags": [
              "Level-4"
            ],
            "insertions": 57,
            "deletions": 1
          },
          {
            "hash": "453dc296ce8979a45dc44db3a18ccb731a51e545",
            "messageTitle": "A-TextUiTesting",
            "messageBody": "",
            "tags": [
              "A-TextUiTesting"
            ],
            "insertions": 77,
            "deletions": 6
          },
          {
            "hash": "097c41fd12ba54bd61169be82660bd44714b382a",
            "messageTitle": "Level 5. Exception Handling",
            "messageBody": "",
            "tags": [
              "Level-5"
            ],
            "insertions": 79,
            "deletions": 45
          },
          {
            "hash": "7f7ad9f7b1f2deec615c537d0126c35e871906ca",
            "messageTitle": "Level 6. Delete",
            "messageBody": "",
            "tags": [
              "Level-6"
            ],
            "insertions": 10,
            "deletions": 1
          }
        ]
      },
      {
        "insertions": 626,
        "deletions": 400,
        "date": "2020-01-30",
        "commitResults": [
          {
            "hash": "39445250a36ef32b4a808a84e57a198cbcb9af77",
            "messageTitle": "Abstract out the bot commands",
            "messageBody": "",
            "insertions": 69,
            "deletions": 38
          },
          {
            "hash": "89c4526c3e80af8200bee9da613ed26beb884669",
            "messageTitle": "Level 7. Save",
            "messageBody": "",
            "tags": [
              "Level-7"
            ],
            "insertions": 100,
            "deletions": 49
          },
          {
            "hash": "53d155434c3d64d71779c81d26e56493b5a70659",
            "messageTitle": "Level 8. Dates and Times",
            "messageBody": "",
            "insertions": 32,
            "deletions": 15
          },
          {
            "hash": "7b2e100fdac3c70e34d217f5ec6a07b73ab07320",
            "messageTitle": "Merge branch 7",
            "messageBody": "",
            "insertions": 100,
            "deletions": 38
          },
          {
            "hash": "5cb9070f9a5c8f6b1ccdd2fd19624cb9570b5220",
            "messageTitle": "Revert \"Merge branch 7\"",
            "messageBody": "This reverts commit 7b2e100fdac3c70e34d217f5ec6a07b73ab07320.\n",
            "insertions": 38,
            "deletions": 100
          },
          {
            "hash": "181c6456d38a08c06592318454dea156841060fa",
            "messageTitle": "A-MoreOOP",
            "messageBody": "",
            "tags": [
              "A-MoreOOP"
            ],
            "insertions": 287,
            "deletions": 160
          }
        ]
      },
      {
        "insertions": 100,
        "deletions": 16,
        "date": "2020-01-31",
        "commitResults": [
          {
            "hash": "2c828b422f7e81ec481708ec99e20e16283c5215",
            "messageTitle": "A-JUnit",
            "messageBody": "",
            "tags": [
              "A-Jar",
              "A-JUnit"
            ],
            "insertions": 69,
            "deletions": 0
          },
          {
            "hash": "4088c479e2be1142d55ff264d7673aaa159211a2",
            "messageTitle": "A-CodingStandard",
            "messageBody": "",
            "insertions": 8,
            "deletions": 8
          },
          {
            "hash": "770ff468910683111c3c0089d1a02206cb156afa",
            "messageTitle": "Level 9. Find",
            "messageBody": "",
            "insertions": 21,
            "deletions": 6
          },
          {
            "hash": "3a88996ed1183f0ac3852bb855e416a886a0716b",
            "messageTitle": "Update Duke.java",
            "messageBody": "",
            "insertions": 2,
            "deletions": 2
          }
        ]
      },
      {
        "insertions": 22,
        "deletions": 6,
        "date": "2020-02-04",
        "commitResults": [
          {
            "hash": "83b77cfcab1d0c266dd5fd39f052752dcc920b1e",
            "messageTitle": "Add exception package",
            "messageBody": "",
            "insertions": 22,
            "deletions": 6
          }
        ]
      },
      {
        "insertions": 121,
        "deletions": 33,
        "date": "2020-02-05",
        "commitResults": [
          {
            "hash": "2e0e0f0641cb91b8a054ee61b79ce3e9995f8e4b",
            "messageTitle": "Checkstyle and Gradle",
            "messageBody": "",
            "insertions": 113,
            "deletions": 20
          },
          {
            "hash": "50c11ef76bb10fdc877579757964e68154dbd00a",
            "messageTitle": "A-Gradle",
            "messageBody": "",
            "tags": [
              "A-Gradle"
            ],
            "insertions": 5,
            "deletions": 8
          },
          {
            "hash": "74152290c23ec5032605595d4b188293318d544f",
            "messageTitle": "A-JavaDoc",
            "messageBody": "",
            "tags": [
              "A-JavaDoc"
            ],
            "insertions": 0,
            "deletions": 2
          },
          {
            "hash": "12f3957508584246016d55929bee5c48342c1463",
            "messageTitle": "Coding Standard",
            "messageBody": "",
            "tags": [
              "A-CodingStandard"
            ],
            "insertions": 3,
            "deletions": 3
          }
        ]
      },
      {
        "insertions": 219,
        "deletions": 3,
        "date": "2020-02-06",
        "commitResults": [
          {
            "hash": "aa824e0c4e502f279740cc9d316be918308d493e",
            "messageTitle": "Level-10. Gui",
            "messageBody": "",
            "tags": [
              "Level-10"
            ],
            "insertions": 219,
            "deletions": 3
          }
        ]
      },
      {
        "insertions": 88,
        "deletions": 26,
        "date": "2020-02-09",
        "commitResults": [
          {
            "hash": "261850512b2984a1f5cf8e222f2206870ebcfb01",
            "messageTitle": "Add packages and jar file",
            "messageBody": "",
            "insertions": 60,
            "deletions": 14
          },
          {
            "hash": "5012219a9539e954e35a6e14ab1fa8a4b94f4177",
            "messageTitle": "A-Assertions and fix todo task input with split(\" \", 2)",
            "messageBody": "",
            "insertions": 28,
            "deletions": 12
          }
        ]
      },
      {
        "insertions": 255,
        "deletions": 192,
        "date": "2020-02-10",
        "commitResults": [
          {
            "hash": "7896e63d6f3cbf0627c7c38a50696f03e77ee583",
            "messageTitle": "Edit Level-9 Find and some refactoring",
            "messageBody": "",
            "tags": [
              "Level-9"
            ],
            "insertions": 254,
            "deletions": 191
          },
          {
            "hash": "76bc7552739ccfe1da9e0d03255bc6448fbfe000",
            "messageTitle": "A-CodeQuality",
            "messageBody": "",
            "tags": [
              "A-CodeQuality"
            ],
            "insertions": 1,
            "deletions": 1
          }
        ]
      },
      {
        "insertions": 100,
        "deletions": 71,
        "date": "2020-02-12",
        "commitResults": [
          {
            "hash": "b697e1dedda4fc505fc4856b0ed7107685c2a900",
            "messageTitle": "Use Lambda and Stream for A-Find",
            "messageBody": "",
            "tags": [
              "A-Streams",
              "A-Lambdas"
            ],
            "insertions": 25,
            "deletions": 19
          },
          {
            "hash": "af09e8898f360d89a0dd39019b903f9228463ce6",
            "messageTitle": "C-MassOps for done and delete",
            "messageBody": "",
            "insertions": 61,
            "deletions": 42
          },
          {
            "hash": "2bfeb9ab019d7b88c0f2df9939244f6d78c90d3f",
            "messageTitle": "A-Assertions",
            "messageBody": "",
            "tags": [
              "A-Assertions"
            ],
            "insertions": 14,
            "deletions": 10
          }
        ]
      }
    ]
  },
  "authorFinalContributionMap": {
    "nhamhung": 1018
  },
  "authorFileTypeContributionMap": {
    "nhamhung": {
      "java": 904,
      "md": 0,
      "fxml": 35,
      "sh": 34,
      "bat": 0,
      "gradle": 35,
      "txt": 10
    }
  },
  "authorContributionVariance": {
    "nhamhung": 41626.15
  },
  "authorDisplayNameMap": {
    "nhamhung": "CS2103T-F10- 1 NHAM..HUNG"
  }
}
